{"v":3,"stories":{"example-introduction--docs":{"id":"example-introduction--docs","title":"Example/Introduction","name":"Docs","importPath":"./stories/Introduction.stories.mdx","storiesImports":[],"standalone":false,"kind":"Example/Introduction","story":"Docs","parameters":{"__id":"example-introduction--docs","docsOnly":true,"fileName":"./stories/Introduction.stories.mdx"}},"shared-component-button--docs":{"id":"shared-component-button--docs","title":"Shared/Component/Button","name":"Docs","importPath":"./stories/Button.stories.tsx","storiesImports":[],"standalone":false,"kind":"Shared/Component/Button","story":"Docs","parameters":{"__id":"shared-component-button--docs","docsOnly":true,"fileName":"./stories/Button.stories.tsx"}},"shared-component-button--primary":{"id":"shared-component-button--primary","title":"Shared/Component/Button","name":"Primary","importPath":"./stories/Button.stories.tsx","kind":"Shared/Component/Button","story":"Primary","parameters":{"__id":"shared-component-button--primary","docsOnly":false,"fileName":"./stories/Button.stories.tsx"}},"shared-component-button--secondary":{"id":"shared-component-button--secondary","title":"Shared/Component/Button","name":"Secondary","importPath":"./stories/Button.stories.tsx","kind":"Shared/Component/Button","story":"Secondary","parameters":{"__id":"shared-component-button--secondary","docsOnly":false,"fileName":"./stories/Button.stories.tsx"}},"shared-component-button--large":{"id":"shared-component-button--large","title":"Shared/Component/Button","name":"Large","importPath":"./stories/Button.stories.tsx","kind":"Shared/Component/Button","story":"Large","parameters":{"__id":"shared-component-button--large","docsOnly":false,"fileName":"./stories/Button.stories.tsx"}},"shared-component-button--small":{"id":"shared-component-button--small","title":"Shared/Component/Button","name":"Small","importPath":"./stories/Button.stories.tsx","kind":"Shared/Component/Button","story":"Small","parameters":{"__id":"shared-component-button--small","docsOnly":false,"fileName":"./stories/Button.stories.tsx"}},"shared-component-header--docs":{"id":"shared-component-header--docs","title":"Shared/Component/Header","name":"Docs","importPath":"./stories/Header.stories.tsx","storiesImports":[],"standalone":false,"kind":"Shared/Component/Header","story":"Docs","parameters":{"__id":"shared-component-header--docs","docsOnly":true,"fileName":"./stories/Header.stories.tsx"}},"shared-component-header--logged-in":{"id":"shared-component-header--logged-in","title":"Shared/Component/Header","name":"Logged In","importPath":"./stories/Header.stories.tsx","kind":"Shared/Component/Header","story":"Logged In","parameters":{"__id":"shared-component-header--logged-in","docsOnly":false,"fileName":"./stories/Header.stories.tsx"}},"shared-component-markdown--docs":{"id":"shared-component-markdown--docs","title":"Shared/Component/Markdown","name":"Docs","importPath":"./stories/Markdown.stories.tsx","storiesImports":[],"standalone":false,"kind":"Shared/Component/Markdown","story":"Docs","parameters":{"__id":"shared-component-markdown--docs","docsOnly":true,"fileName":"./stories/Markdown.stories.tsx"}},"shared-component-markdown--simple":{"id":"shared-component-markdown--simple","title":"Shared/Component/Markdown","name":"Simple","importPath":"./stories/Markdown.stories.tsx","kind":"Shared/Component/Markdown","story":"Simple","parameters":{"__id":"shared-component-markdown--simple","docsOnly":false,"fileName":"./stories/Markdown.stories.tsx"}}}}
